nacos_mcp_router/__init__.py
nacos_mcp_router/__main__.py
nacos_mcp_router/auth.py
nacos_mcp_router/constants.py
nacos_mcp_router/logger.py
nacos_mcp_router/mcp_manager.py
nacos_mcp_router/md5_util.py
nacos_mcp_router/nacos_http_client.py
nacos_mcp_router/nacos_mcp_server_config.py
nacos_mcp_router/router.py
nacos_mcp_router/router_exceptions.py
nacos_mcp_router/router_types.py
nacos_mcp_router-0.2.1.dist-info/METADATA
nacos_mcp_router-0.2.1.dist-info/WHEEL
nacos_mcp_router-0.2.1.dist-info/entry_points.txt
nacos_mcp_router-0.2.1.dist-info/RECORD
