Metadata-Version: 2.4
Name: nacos_mcp_router
Version: 0.2.1
Summary: Add your description here
Requires-Python: >=3.12
Requires-Dist: chromadb>=1.0.5
Requires-Dist: mcp>=1.9.4
Requires-Dist: requests>=2.32.3
